internumpi/__init__.py
internumpi/distributeData.py
internumpi/interpolate.py
internumpi/main.py
internumpi-0.0.2.dist-info/LICENCE
internumpi-0.0.2.dist-info/METADATA
internumpi-0.0.2.dist-info/WHEEL
internumpi-0.0.2.dist-info/top_level.txt
internumpi-0.0.2.dist-info/RECORD
