Metadata-Version: 2.1
Name: internumpi
Version: 0.0.2
Summary: For interpolating 3D data
Home-page: https://gitlab.com/chaitanyaupp18/interpolaton.git
Author: Chaitanya Mamatha Ananda
Author-email: chaitanyaupp18@gmail.com
License: UNKNOWN
Platform: UNKNOWN
Classifier: Programming Language :: Python :: 3
Classifier: License :: OSI Approved :: MIT License
Classifier: Operating System :: OS Independent
Requires-Python: >=3.7
License-File: LICENCE
